docs/conf.py
peptdeep/__init__.py
peptdeep/cli.py
peptdeep/cli_argparse.py
peptdeep/gui.py
peptdeep/pipeline_api.py
peptdeep/pretrained_models.py
peptdeep/settings.py
peptdeep/constants/__init__.py
peptdeep/constants/_const.py
peptdeep/constants/default_settings.yaml
peptdeep/constants/model_const.yaml
peptdeep/hla/__init__.py
peptdeep/hla/hla_class1.py
peptdeep/hla/hla_utils.py
peptdeep/mass_spec/__init__.py
peptdeep/mass_spec/mass_calibration.py
peptdeep/mass_spec/match.py
peptdeep/mass_spec/ms_reader.py
peptdeep/model/__init__.py
peptdeep/model/base.py
peptdeep/model/building_block.py
peptdeep/model/ccs.py
peptdeep/model/charge.py
peptdeep/model/featurize.py
peptdeep/model/generic_property_prediction.py
peptdeep/model/model_interface.py
peptdeep/model/model_shop.py
peptdeep/model/ms2.py
peptdeep/model/rt.py
peptdeep/protein/__init__.py
peptdeep/protein/fasta.py
peptdeep/psm_frag_reader/__init__.py
peptdeep/psm_frag_reader/maxquant_frag_reader.py
peptdeep/psm_frag_reader/psm_frag_reader.py
peptdeep/psm_frag_reader/psmlabel_reader.py
peptdeep/rescore/__init__.py
peptdeep/rescore/fdr.py
peptdeep/rescore/feature_extractor.py
peptdeep/rescore/percolator.py
peptdeep/spec_lib/__init__.py
peptdeep/spec_lib/library_factory.py
peptdeep/spec_lib/predict_lib.py
peptdeep/spec_lib/translate.py
peptdeep/utils/__init__.py
peptdeep/utils/_pyinstaller_hooks.py
peptdeep/utils/deprecations.py
peptdeep/utils/device_utils.py
peptdeep/utils/logger.py
peptdeep/utils/regression.py
peptdeep/webui/__init__.py
peptdeep/webui/library_ui.py
peptdeep/webui/main_ui.py
peptdeep/webui/model_ui.py
peptdeep/webui/rescore_ui.py
peptdeep/webui/server.py
peptdeep/webui/server_ui.py
peptdeep/webui/settings_ui.py
peptdeep/webui/startpage.py
peptdeep/webui/transfer_ui.py
peptdeep/webui/ui_utils.py
peptdeep/webui/logos/peptdeep.ico
peptdeep/webui/logos/peptdeep.png
peptdeep-1.4.0.dist-info/licenses/LICENSE.txt
release/pyinstaller/peptdeep_cli_pyinstaller.py
release/pyinstaller/peptdeep_pyinstaller.py
requirements/requirements.txt
peptdeep-1.4.0.dist-info/METADATA
peptdeep-1.4.0.dist-info/WHEEL
peptdeep-1.4.0.dist-info/entry_points.txt
peptdeep-1.4.0.dist-info/top_level.txt
peptdeep-1.4.0.dist-info/RECORD
