Metadata-Version: 2.4
Name: peptdeep
Version: 1.4.0
Summary: The AlphaX deep learning framework for Proteomics
Author-email: Mann Labs <jalew.zwf@qq.com>
License:                                  Apache License
Project-URL: Paper preprint, https://www.biochem.mpg.de/mann
Project-URL: Repository, https://github.com/MannLabs/peptdeep
Project-URL: Issues, https://github.com/MannLabs/peptdeep/issues
Project-URL: Mann Labs Homepage, https://www.biochem.mpg.de/mann
Project-URL: Docs, https://alphapeptdeep.readthedocs.io/en/latest/
Project-URL: PyPi, https://pypi.org/project/peptdeep/
Keywords: mass spectrometry,proteomics,search engine,DIA,data-independent acquisition,bioinformatics,AlphaPept,AlphaPept ecosystem,deep learning,AlphaX ecosystem
Classifier: Development Status :: 5 - Production/Stable
Classifier: Intended Audience :: Science/Research
Classifier: License :: OSI Approved :: Apache Software License
Classifier: Operating System :: OS Independent
Classifier: Programming Language :: Python :: 3
Classifier: Topic :: Scientific/Engineering :: Bio-Informatics
Requires-Python: >=3.8.0
License-File: LICENSE.txt
Requires-Dist: pywin32; sys_platform == "win32"
Requires-Dist: pythonnet; sys_platform == "win32"
Requires-Dist: click
Requires-Dist: pandas
Requires-Dist: numpy<2
Requires-Dist: torch
Requires-Dist: tqdm
Requires-Dist: numba
Requires-Dist: psutil
Requires-Dist: transformers
Requires-Dist: scikit-learn
Requires-Dist: lxml
Requires-Dist: pyteomics
Requires-Dist: alphabase>=1.5.0
Requires-Dist: alpharaw>=0.2.0
Provides-Extra: stable
Requires-Dist: pywin32==308; sys_platform == "win32" and extra == "stable"
Requires-Dist: pythonnet==3.0.4; sys_platform == "win32" and extra == "stable"
Requires-Dist: click==8.1.7; extra == "stable"
Requires-Dist: pandas==2.2.3; extra == "stable"
Requires-Dist: numpy<2; extra == "stable"
Requires-Dist: torch==2.5.1; (sys_platform != "darwin" or platform_machine != "x86_64") and extra == "stable"
Requires-Dist: torch==2.2.2; (sys_platform == "darwin" and platform_machine == "x86_64") and extra == "stable"
Requires-Dist: tqdm==4.67.1; extra == "stable"
Requires-Dist: numba==0.60.0; extra == "stable"
Requires-Dist: psutil==6.1.0; extra == "stable"
Requires-Dist: transformers==4.47.0; extra == "stable"
Requires-Dist: scikit-learn==1.6.0; extra == "stable"
Requires-Dist: lxml==5.3.0; extra == "stable"
Requires-Dist: pyteomics==4.7.5; extra == "stable"
Requires-Dist: alphabase>=1.5.0; extra == "stable"
Requires-Dist: alpharaw>=0.2.0; extra == "stable"
Provides-Extra: gui
Requires-Dist: streamlit>=1.23.0; extra == "gui"
Requires-Dist: streamlit-aggrid; extra == "gui"
Provides-Extra: gui-stable
Requires-Dist: streamlit==1.40.2; extra == "gui-stable"
Requires-Dist: streamlit-aggrid==1.0.5; extra == "gui-stable"
Provides-Extra: hla
Requires-Dist: pydivsufsort; extra == "hla"
Provides-Extra: hla-stable
Requires-Dist: pydivsufsort; extra == "hla-stable"
Provides-Extra: docs
Requires-Dist: autodocsumm; extra == "docs"
Requires-Dist: myst_parser; extra == "docs"
Requires-Dist: sphinx; extra == "docs"
Requires-Dist: nbsphinx; extra == "docs"
Requires-Dist: jinja2; extra == "docs"
Requires-Dist: contextfilter; extra == "docs"
Requires-Dist: furo; extra == "docs"
Provides-Extra: tests
Requires-Dist: pytest; extra == "tests"
Requires-Dist: pre-commit==3.7.0; extra == "tests"
Requires-Dist: nbmake==1.5.3; extra == "tests"
Requires-Dist: seaborn; extra == "tests"
Provides-Extra: development
Requires-Dist: jupyter; extra == "development"
Requires-Dist: ipykernel; extra == "development"
Requires-Dist: autodocsumm; extra == "development"
Requires-Dist: myst_parser; extra == "development"
Requires-Dist: sphinx; extra == "development"
Requires-Dist: nbsphinx; extra == "development"
Requires-Dist: jinja2; extra == "development"
Requires-Dist: contextfilter; extra == "development"
Requires-Dist: furo; extra == "development"
Requires-Dist: pytest; extra == "development"
Requires-Dist: pre-commit==3.7.0; extra == "development"
Requires-Dist: nbmake==1.5.3; extra == "development"
Requires-Dist: seaborn; extra == "development"
Dynamic: license-file
